rpa_ebay/__init__.py
rpa_ebay/api/__init__.py
rpa_ebay/command/__init__.py
rpa_ebay/command/bill/__init__.py
rpa_ebay/command/bill/service/__init__.py
rpa_ebay/request/__init__.py
rpa_ebay/service/__init__.py
rpa_ebay-1.0.0.dist-info/LICENSE
rpa_ebay-1.0.0.dist-info/METADATA
rpa_ebay-1.0.0.dist-info/WHEEL
rpa_ebay-1.0.0.dist-info/top_level.txt
rpa_ebay-1.0.0.dist-info/RECORD
